main.py
api/__init__.py
api/auth.py
api/generate_icons.py
api/mobile_server.py
api/rate_limit.py
api/schemas.py
api/server.py
api/webapp.py
audit/__init__.py
audit/export.py
audit/integrity.py
audit/log.py
audit/reader.py
audit/verify.py
cli/__init__.py
cli/benchmarks.py
cli/brain.py
cli/error_handling.py
cli/mobile_helpers.py
cli/registry.py
cli/commands/__init__.py
cli/commands/analyze.py
cli/commands/auth.py
cli/commands/chat.py
cli/commands/cmd.py
cli/commands/config.py
cli/commands/enhance.py
cli/commands/fix.py
cli/commands/init.py
cli/commands/mobile.py
cli/commands/quickstart.py
cli/commands/reset.py
cli/commands/review.py
cli/commands/run.py
cli/commands/setup.py
cli/commands/smartfix.py
cli/commands/status.py
cli/commands/sync.py
cli/commands/test.py
cli/commands/ui.py
cli/commands/usage.py
cli/commands/workspace.py
control/__init__.py
control/login.py
control/model_selector.py
control/profile_wizard.py
control/setup.py
control/state.py
control/auth/__init__.py
control/auth/key_store.py
control/auth/login_flow.py
control/auth/validator.py
core/__init__.py
core/brain.py
core/brain_orchestrator.py
core/code_optimizer.py
core/executor.py
core/identity.py
core/intent.py
core/orchestrator.py
core/orchestrator_factory.py
core/planner.py
core/policy.py
core/reasoning.py
core/risk.py
core/security_scanner.py
core/sentry_config.py
core/syntax_analyzer.py
core/vibe.py
domains/__init__.py
domains/_boundary.py
domains/_enforcer.py
guardrails/__init__.py
guardrails/kill_switch.py
guardrails/kill_switch_verify.py
guardrails/roles_registry.py
guardrails/validators.py
intel/__init__.py
intel/approval.py
intel/assess.py
intel/code_intelligence.py
intel/intake.py
intel/kill_switch.py
intel/normalize.py
intel/scheduler.py
intel/types.py
intel/verify.py
knowledge/__init__.py
knowledge/manager.py
memory/__init__.py
memory/audit_index.py
memory/long_term.py
memory/short_term.py
memory/task_memory.py
memory/working_memory.py
models/__init__.py
models/base.py
models/config.py
anox-1.0.2.dist-info/METADATA
anox-1.0.2.dist-info/WHEEL
anox-1.0.2.dist-info/entry_points.txt
anox-1.0.2.dist-info/top_level.txt
anox-1.0.2.dist-info/RECORD
