Metadata-Version: 2.4
Name: anox
Version: 1.0.2
Summary: ANOX — AI-Powered Development Assistant
Home-page: https://github.com/HakunoKun/Ai-Brain
Author: HakunoKun
Keywords: ai assistant development cli chat
Classifier: Development Status :: 4 - Beta
Classifier: Intended Audience :: Developers
Classifier: Topic :: Software Development :: Libraries :: Application Frameworks
Classifier: Programming Language :: Python :: 3
Classifier: Programming Language :: Python :: 3.8
Classifier: Programming Language :: Python :: 3.9
Classifier: Programming Language :: Python :: 3.10
Classifier: Programming Language :: Python :: 3.11
Classifier: Programming Language :: Python :: 3.12
Requires-Python: >=3.8
Requires-Dist: fastapi>=0.104.0
Requires-Dist: uvicorn[standard]>=0.24.0
Requires-Dist: websockets>=12.0
Requires-Dist: pydantic>=2.5.0
Requires-Dist: httpx>=0.25.0
Requires-Dist: aiohttp>=3.9.0
Requires-Dist: PyYAML>=6.0
Requires-Dist: tree-sitter>=0.20.0
Requires-Dist: pylint>=3.0.0
Requires-Dist: radon>=6.0.0
Requires-Dist: bandit>=1.7.5
Requires-Dist: prompt-toolkit>=3.0.0
Requires-Dist: rich>=13.7.0
Requires-Dist: pyngrok>=7.0.0
Requires-Dist: python-dotenv>=1.0.0
Requires-Dist: sentry-sdk>=1.40.0
Requires-Dist: pick>=2.0.0
Dynamic: author
Dynamic: classifier
Dynamic: description
Dynamic: description-content-type
Dynamic: home-page
Dynamic: keywords
Dynamic: requires-dist
Dynamic: requires-python
Dynamic: summary
